omnicart_pipeline/__init__.py
omnicart_pipeline/api_client.py
omnicart_pipeline/cli.py
omnicart_pipeline/config.py
omnicart_pipeline/data_analyzer.py
omnicart_pipeline/data_enricher.py
omnicart_pipeline/exporter.py
omnicart_pipeline/logging_config.py
omnicart_pipeline/pipeline.cfg
omnicart_pipeline/pipeline.py
omnicart_pipeline-0.1.2.dist-info/entry_points.txt
omnicart_pipeline-0.1.2.dist-info/METADATA
omnicart_pipeline-0.1.2.dist-info/WHEEL
omnicart_pipeline-0.1.2.dist-info/RECORD
